Workbook

Sheet 1_原価計算
A1: マイフォーチューン — 原価・コスト分析
A2: ■ 青文字=入力値（変更可） ■ 黒文字=計算式 ■ 緑文字=他シート参照
A4: 【基本前提】
A5: USD/JPY レート | B5: 155 | C5: 円
A6: 1回の占いあたり 入力トークン | B6: 800 | C6: tokens
A7: 1回の占いあたり 出力トークン | B7: 600 | C7: tokens
A9: 【AI APIコスト（1回の占いあたり）】
A10: プロバイダー | B10: 入力 $/M tokens | C10: 出力 $/M tokens | D10: 1回コスト($) | E10: 1回コスト(¥) | F10: 備考 | G10: 優先順
A11: DeepSeek deepseek-chat | B11: 0.14 | C11: 0.28 | D11: =(B6*B11+B7*C11)/1000000 | E11: =D11*B5 | F11: 主力プロバイダー（最安） | G11: 1
A12: Gemini 2.0 Flash Lite | B12: 0.075 | C12: 0.3 | D12: =(B6*B12+B7*C12)/1000000 | E12: =D12*B5 | F12: フォールバック① | G12: 2
A13: Claude Haiku 4.5 | B13: 0.8 | C13: 4 | D13: =(B6*B13+B7*C13)/1000000 | E13: =D13*B5 | F13: フォールバック②（最終） | G13: 3
A15: 【プランごとのユーザー1人あたり 月間AIコスト】
A16: プラン | B16: 月間占い回数上限 | C16: DeepSeek使用時(¥) | D16: Gemini使用時(¥) | E16: Claude使用時(¥) | F16: 主力想定コスト(¥)
A17: Free（無料） | B17: 10 | C17: =B17*E11 | D17: =B17*E12 | E17: =B17*E13 | F17: =C17
A18: Light（¥680/月） | B18: 50 | C18: =B18*E11 | D18: =B18*E12 | E18: =B18*E13 | F18: =C18
A19: Pro（¥1,500/月） | B19: 300 | C19: =B19*E11 | D19: =B19*E12 | E19: =B19*E13 | F19: =C19
A21: 【Google Play 手数料と純売上】
A22: プラン | B22: 定価(¥) | C22: 手数料率（1年目30%） | D22: 手数料率（2年目~15%） | E22: 純売上1年目(¥) | F22: 純売上2年目~(¥)
A23: Lightプラン | B23: 680 | C23: 0.3 | D23: 0.15 | E23: =B23*(1-C23) | F23: =B23*(1-D23)
A24: Proプラン | B24: 1500 | C24: 0.3 | D24: 0.15 | E24: =B24*(1-C24) | F24: =B24*(1-D24)
A27: ※ 入力値（青）は実際の料金体系変更時に更新してください。手数料率はGoogle Play Small Business Program適用を前提（年間$1M以下）

Sheet 2_収益シミュレーション
A1: マイフォーチューン — 収益シミュレーション（3シナリオ）
A3: 【シナリオ前提（青文字を変更してシミュレーション）】
A4: 前提項目 | B4: 保守的 | C4: 標準 | D4: 楽観的 | F4: 説明
A5: 月間新規DL数（人） | B5: 500 | C5: 2000 | D5: 5000 | F5: アプリストアからの新規インストール数/月
A6: 累積アクティブユーザー（6ヶ月後） | B6: 1500 | C6: 8000 | D6: 25000 | F6: 継続利用ユーザーの推定累積数
A7: 有料転換率 | B7: 0.015 | C7: 0.03 | D7: 0.05 | F7: Free→有料プランへの転換率
A8: Lightプラン比率（有料中） | B8: 0.7 | C8: 0.65 | D8: 0.6 | F8: 有料ユーザーのうちLightプラン加入割合
A9: 月次チャーン率（解約率） | B9: 0.08 | C9: 0.05 | D9: 0.03 | F9: 有料ユーザーの月次解約率
A10: DeepSeek 1回コスト(¥) ※Sheet1参照 | B10: ='1_原価計算'!E11 | C10: ='1_原価計算'!E11 | D10: ='1_原価計算'!E11 | F10: 占い1回あたりのAIコスト
A11: Light月間利用回数（想定） | B11: 40 | C11: 45 | D11: 50 | F11: 実際の使用回数（上限50）
A12: Pro月間利用回数（想定） | B12: 150 | C12: 200 | D12: 280 | F12: 実際の使用回数（上限300）
A14: 【月次収益・コスト・利益（6ヶ月後 安定期）】
A15: 計算項目 | B15: 保守的 | C15: 標準 | D15: 楽観的 | F15: 計算式メモ
A16: 有料ユーザー総数（人） | B16: =ROUND(B6*B7,0) | C16: =ROUND(C6*C7,0) | D16: =ROUND(D6*D7,0) | F16: 累積ユーザー × 転換率
A17: うち Lightプラン（人） | B17: =ROUND(B16*B8,0) | C17: =ROUND(C16*C8,0) | D17: =ROUND(D16*D8,0) | F17: 有料総数 × Light比率
A18: うち Proプラン（人） | B18: =ROUND(B16*(1-B8),0) | C18: =ROUND(C16*(1-C8),0) | D18: =ROUND(D16*(1-D8),0) | F18: 有料総数 × (1-Light比率)
A19: 月間売上（Light） | B19: =B17*'1_原価計算'!E23 | C19: =C17*'1_原価計算'!E23 | D19: =D17*'1_原価計算'!E23 | F19: Light人数 × 純売上単価(¥)
A20: 月間売上（Pro） | B20: =B18*'1_原価計算'!E24 | C20: =C18*'1_原価計算'!E24 | D20: =D18*'1_原価計算'!E24 | F20: Pro人数 × 純売上単価(¥)
A21: 月間売上合計 | B21: =B19+B20 | C21: =C19+C20 | D21: =D19+D20 | F21: Light売上 + Pro売上
A22: 月間AIコスト（Freeユーザー） | B22: =MAX(0,B6-B16)*10*B10 | C22: =MAX(0,C6-C16)*10*C10 | D22: =MAX(0,D6-D16)*10*D10 | F22: Free人数 × 10回 × 1回コスト
A23: 月間AIコスト（Light） | B23: =B17*B11*B10 | C23: =C17*C11*C10 | D23: =D17*D11*D10 | F23: Light人数 × 想定利用回数 × 1回コスト
A24: 月間AIコスト（Pro） | B24: =B18*B12*B10 | C24: =C18*C12*C10 | D24: =D18*D12*D10 | F24: Pro人数 × 想定利用回数 × 1回コスト
A25: 月間AIコスト合計 | B25: =B22+B23+B24 | C25: =C22+C23+C24 | D25: =D22+D23+D24 | F25: 全AIコスト合計
A26: Firebase/インフラコスト | B26: 500 | C26: 1000 | D26: 3000 | F26: 小規模は無料枠内を想定
A27: 月間純利益 | B27: =B21-B25-B26 | C27: =C21-C25-C26 | D27: =D21-D25-D26 | F27: 売上 - AIコスト - インフラ
A28: 利益率 | B28: =IF(B21=0,"-",B27/B21) | C28: =IF(C21=0,"-",C27/C21) | D28: =IF(D21=0,"-",D27/D21) | F28: 純利益 ÷ 売上
A29: 損益分岐点（有料ユーザー数） | B29: =IFERROR(ROUND(B26/('1_原価計算'!E23*B8+'1_原価計算'!E24*(1-B8)-B10*(B8*B11+(1-B8)*B12)),0),"計算不可") | C29: =IFERROR(ROUND(C26/('1_原価計算'!E23*C8+'1_原価計算'!E24*(1-C8)-C10*(C8*C11+(1-C8)*C12)),0),"計算不可") | D29: =IFERROR(ROUND(D26/('1_原価計算'!E23*D8+'1_原価計算'!E24*(1-D8)-D10*(D8*D11+(1-D8)*D12)),0),"計算不可") | F29: 固定コスト ÷ 1ユーザー限界利益
A32: 【セグメント別・全体利益率分析】
A33: 利益率 | B33: 保守的 | C33: 標準 | D33: 楽観的 | F33: 計算式
A34: Freeセグメント 利益率 | B34: =IF(B16=0,"-",-B22/B22) | C34: =IF(C16=0,"-",-C22/C22) | D34: =IF(D16=0,"-",-D22/D22) | F34: Free: -100% (コストのみ、売上なし)
A35: Lightセグメント 利益率 | B35: =IF(B17=0,"-",(B19-B23)/B19) | C35: =IF(C17=0,"-",(C19-C23)/C19) | D35: =IF(D17=0,"-",(D19-D23)/D19) | F35: (セグメント売上 - セグメントAIコスト) / セグメント売上
A36: Proセグメント 利益率 | B36: =IF(B18=0,"-",(B20-B24)/B20) | C36: =IF(C18=0,"-",(C20-C24)/C20) | D36: =IF(D18=0,"-",(D20-D24)/D20) | F36: (セグメント売上 - セグメントAIコスト) / セグメント売上
A37: 全体 利益率（全ユーザー平均） | B37: =IF(B21=0,"-",(B21-B25-B26)/B21) | C37: =IF(C21=0,"-",(C21-C25-C26)/C21) | D37: =IF(D21=0,"-",(D21-D25-D26)/D21) | F37: (全売上 - 全AIコスト - インフラ) / 全売上
A39: ※ Freeユーザーは売上0なため利益率-100%（コスト負担のみ）。有料ユーザーのアップセルと継続率向上が収益性向上のカギ。

Sheet 3_価格感応度
A1: マイフォーチューン — 価格感応度分析
A3: 【前提: 価格弾力性の仮定（標準シナリオベース）】
A4: 標準シナリオ 累積ユーザー数 | B4: 8000
A5: 基準転換率（¥680/¥1,500時） | B5: 0.03
A6: 価格弾力性（10%値上げ→転換率X%減） | B6: 0.05
A7: Light:Pro比率（固定） | B7: 0.65
A8: Google Play手数料 | B8: 0.3
A10: 【Lightプラン 価格変更シミュレーション（Proは¥1,500固定）】
A11: Lightプラン価格 | B11: 価格変化率 | C11: 調整後転換率 | D11: 有料ユーザー数 | E11: Light人数 | F11: Pro人数 | G11: 月間売上合計 | H11: 現行との差
A12: 480 | B12: =(A12-680)/680 | C12: =MAX(0.001,B5*(1-B6*(A12-680)/680)) | D12: =ROUND(B4*C12,0) | E12: =ROUND(D12*B7,0) | F12: =D12-E12 | G12: =E12*A12*(1-B8)+F12*1500*(1-B8) | H12: =G12-G14
A13: 580 | B13: =(A13-680)/680 | C13: =MAX(0.001,B5*(1-B6*(A13-680)/680)) | D13: =ROUND(B4*C13,0) | E13: =ROUND(D13*B7,0) | F13: =D13-E13 | G13: =E13*A13*(1-B8)+F13*1500*(1-B8) | H13: =G13-G14
A14: 680 | B14: =(A14-680)/680 | C14: =MAX(0.001,B5*(1-B6*(A14-680)/680)) | D14: =ROUND(B4*C14,0) | E14: =ROUND(D14*B7,0) | F14: =D14-E14 | G14: =E14*A14*(1-B8)+F14*1500*(1-B8) | H14: =G14-G14
A15: 780 | B15: =(A15-680)/680 | C15: =MAX(0.001,B5*(1-B6*(A15-680)/680)) | D15: =ROUND(B4*C15,0) | E15: =ROUND(D15*B7,0) | F15: =D15-E15 | G15: =E15*A15*(1-B8)+F15*1500*(1-B8) | H15: =G15-G14
A16: 980 | B16: =(A16-680)/680 | C16: =MAX(0.001,B5*(1-B6*(A16-680)/680)) | D16: =ROUND(B4*C16,0) | E16: =ROUND(D16*B7,0) | F16: =D16-E16 | G16: =E16*A16*(1-B8)+F16*1500*(1-B8) | H16: =G16-G14
A19: 【Proプラン 価格変更シミュレーション（Lightは¥680固定）】
A20: Lightプラン価格 | B20: 価格変化率 | C20: 調整後転換率 | D20: 有料ユーザー数 | E20: Light人数 | F20: Pro人数 | G20: 月間売上合計 | H20: 現行との差
A21: 980 | B21: =(A21-1500)/1500 | C21: =MAX(0.001,B5*(1-B6*(A21-1500)/1500)) | D21: =ROUND(B4*C21,0) | E21: =ROUND(D21*B7,0) | F21: =D21-E21 | G21: =E21*680*(1-B8)+F21*A21*(1-B8) | H21: =G21-G23
A22: 1200 | B22: =(A22-1500)/1500 | C22: =MAX(0.001,B5*(1-B6*(A22-1500)/1500)) | D22: =ROUND(B4*C22,0) | E22: =ROUND(D22*B7,0) | F22: =D22-E22 | G22: =E22*680*(1-B8)+F22*A22*(1-B8) | H22: =G22-G23
A23: 1500 | B23: =(A23-1500)/1500 | C23: =MAX(0.001,B5*(1-B6*(A23-1500)/1500)) | D23: =ROUND(B4*C23,0) | E23: =ROUND(D23*B7,0) | F23: =D23-E23 | G23: =E23*680*(1-B8)+F23*A23*(1-B8) | H23: =G23-G23
A24: 1800 | B24: =(A24-1500)/1500 | C24: =MAX(0.001,B5*(1-B6*(A24-1500)/1500)) | D24: =ROUND(B4*C24,0) | E24: =ROUND(D24*B7,0) | F24: =D24-E24 | G24: =E24*680*(1-B8)+F24*A24*(1-B8) | H24: =G24-G23
A25: 2200 | B25: =(A25-1500)/1500 | C25: =MAX(0.001,B5*(1-B6*(A25-1500)/1500)) | D25: =ROUND(B4*C25,0) | E25: =ROUND(D25*B7,0) | F25: =D25-E25 | G25: =E25*680*(1-B8)+F25*A25*(1-B8) | H25: =G25-G23

Sheet 4_競合比較
A1: マイフォーチューン — 競合比較・価格妥当性
A3: アプリ/サービス | B3: 月額料金（下限） | C3: 月額料金（上限） | D3: AI機能 | E3: パーソナライズ | F3: 占術数 | G3: 差別化ポイント比較
A4: ── ホロスコープ系 ──
A5: ザ・ホロスコープ | B5: 480 | C5: 980 | D5: なし | E5: 低 | F5: 3〜5 | G5: 星座・月星座に特化
A6: 星占いパーフェクト | B6: 0 | C6: 480 | D6: なし | E6: 低 | F6: 3 | G6: 無料中心、広告収入
A7: Astro by Astrocenter | B7: 980 | C7: 1480 | D7: あり | E7: 中 | F7: 8〜10 | G7: 海外発、英語コンテンツ中心
A8: ── タロット系 ──
A9: ゴールデンタロット | B9: 0 | C9: 480 | D9: なし | E9: 低 | F9: 1 | G9: タロット特化、無料
A10: タロット占い Premium | B10: 480 | C10: 780 | D10: なし | E10: 低 | F10: 2〜3 | G10: シンプルUI
A11: ── 総合占い系 ──
A12: Uranai Premium | B12: 480 | C12: 1200 | D12: なし | E12: 中 | F12: 6〜8 | G12: 複数占術、日本語特化
A13: 占いアプリ総合 | B13: 380 | C13: 980 | D13: なし | E13: 低 | F13: 5〜8 | G13: コンテンツ量重視
A14: ── リアル占いサービス ──
A15: 電話占い（相場） | B15: 18000 | C15: 60000 | D15: なし | E15: 高 | F15: 多数 | G15: 30分〜2時間 × ¥300〜400/分
A16: チャット占い（相場） | B16: 1500 | C16: 6000 | D16: なし | E16: 高 | F16: 多数 | G16: 1回ごと課金
A17: ── マイフォーチューン ──
A18: マイフォーチューン Light | B18: 680 | C18: 680 | D18: あり | E18: 高 | F18: 10+ | G18: ★AI記憶型・過去履歴学習・50回/月
A19: マイフォーチューン Pro | B19: 1500 | C19: 1500 | D19: あり | E19: 高 | F19: 10+ | G19: ★AIパーソナライズ強化・300回/月・四柱推命・縁起カレンダー
A22: 【価格妥当性 まとめ】
A23: ✅ Light ¥680：競合の標準価格帯（¥480〜¥980）の中央値以下。AI記憶型は希少で差別化高い。値上げ余地あり（¥780〜¥880）。
A24: ✅ Pro ¥1,500：総合占いアプリの最高値帯だが、300回/月 × AI分析 × 四柱推命で正当化可能。電話占い比では圧倒的コスパ。
A25: ⚠️ Free枠（10回/月）：競合無料プランと比較して少なめ。初期獲得のため15〜20回程度への増加を検討。
A26: 💡 推奨価格案：Light ¥780 / Pro ¥1,680。弾力性試算で標準シナリオ収益が約15〜20%向上見込み（Sheet3参照）。
